XMFlib/__init__.py
XMFlib/PairProbML/__init__.py
XMFlib/PairProbML/io.py
XMFlib/PairProbML/models.py
XMFlib/PairProbML/predictor.py
XMFlib/PairProbML/utils.py
XMFlib/PairProbML/models/mlp_a2p_100.pth
XMFlib/PairProbML/models/mlp_a2p_111.pth
XMFlib/PairProbML/models/mlp_a2p_111_2nn.pth
xmflib-0.1.8.dist-info/licenses/LICENCE
xmflib-0.1.8.dist-info/METADATA
xmflib-0.1.8.dist-info/WHEEL
xmflib-0.1.8.dist-info/top_level.txt
xmflib-0.1.8.dist-info/RECORD
