Metadata-Version: 2.4
Name: XMFlib
Version: 0.1.8
Summary: A library for pair probability prediction using machine learning.
Author-email: Minhui Li <23210220016@m.fudan.edu.cn>
License: MIT License
Project-URL: Homepage, https://github.com/aFui233/XMFlib
Project-URL: Repository, https://github.com/aFui233/XMFlib
Requires-Python: >=3.7
License-File: LICENCE
Requires-Dist: torch>=2.4.0
Requires-Dist: numpy>=2.0.2
Dynamic: license-file
